liepy-0.1.4.dist-info/METADATA
liepy-0.1.4.dist-info/WHEEL
liepy-0.1.4.dist-info/license_files/LICENSE
liepy.libs/libgfortran-a02ca2f2.so.5
liepy.libs/libopenblas-ac4e3ab0.so.0
liepy.libs/libgomp-71731c74.so.1
liepy/__init__.py
liepy/liepy.cpython-311-x86_64-linux-gnu.so
liepy-0.1.4.dist-info/RECORD
